<?xml version="1.0" encoding="UTF-8"?>
<issues format="6" by="lint 8.8.0" type="baseline" client="gradle" dependencies="false" name="AGP (8.8.0)" variant="all" version="8.8.0">

    <issue
        id="DefaultLocale"
        message="Implicitly using the default locale is a common source of bugs: Use `String.format(Locale, ...)` instead"
        errorLine1="        return String.format(&quot;[Elapsed: %ds, Receiver: %s]&quot;,"
        errorLine2="               ^">
        <location
            file="src/main/java/com/northcoders/pigliotech_frontend/activities/BackendColdStartActivity.java"
            line="54"
            column="16"/>
    </issue>

    <issue
        id="DefaultLocale"
        message="Implicitly using the default locale is a common source of bugs: Use `String.format(Locale, ...)` instead"
        errorLine1="            elapsedTimeTextView.setText(String.format(&quot;Time elapsed: %d min %d sec&quot;,"
        errorLine2="                                        ^">
        <location
            file="src/main/java/com/northcoders/pigliotech_frontend/activities/BackendColdStartActivity.java"
            line="192"
            column="41"/>
    </issue>

    <issue
        id="DefaultLocale"
        message="Implicitly using the default locale is a common source of bugs: Use `String.format(Locale, ...)` instead"
        errorLine1="                logInfo(String.format(&quot;Waiting %d ms before next retry (attempt %d/%d) - Next retry at: %s&quot;,"
        errorLine2="                        ^">
        <location
            file="src/main/java/com/northcoders/pigliotech_frontend/utils/BackendStatusManager.java"
            line="190"
            column="25"/>
    </issue>

    <issue
        id="DefaultLocale"
        message="Implicitly using the default locale is a common source of bugs: Use `String.format(Locale, ...)` instead"
        errorLine1="                        logInfo(String.format(&quot;Quick ping successful with code: %d - Response time: %d ms&quot;,"
        errorLine2="                                ^">
        <location
            file="src/main/java/com/northcoders/pigliotech_frontend/utils/BackendStatusManager.java"
            line="261"
            column="33"/>
    </issue>

    <issue
        id="DefaultLocale"
        message="Implicitly using the default locale is a common source of bugs: Use `String.format(Locale, ...)` instead"
        errorLine1="                        logWarning(String.format(&quot;Quick ping failed with code: %d - Response time: %d ms&quot;,"
        errorLine2="                                   ^">
        <location
            file="src/main/java/com/northcoders/pigliotech_frontend/utils/BackendStatusManager.java"
            line="265"
            column="36"/>
    </issue>

    <issue
        id="DefaultLocale"
        message="Implicitly using the default locale is a common source of bugs: Use `String.format(Locale, ...)` instead"
        errorLine1="                    logWarning(String.format(&quot;Quick ping failed: %s - Response time: %d ms&quot;,"
        errorLine2="                               ^">
        <location
            file="src/main/java/com/northcoders/pigliotech_frontend/utils/BackendStatusManager.java"
            line="277"
            column="32"/>
    </issue>

    <issue
        id="DefaultLocale"
        message="Implicitly using the default locale is a common source of bugs: Use `String.format(Locale, ...)` instead"
        errorLine1="            logInfo(String.format(&quot;Pinging backend (attempt %d/%d) - User wait time: %d min %d sec&quot;,"
        errorLine2="                    ^">
        <location
            file="src/main/java/com/northcoders/pigliotech_frontend/utils/BackendStatusManager.java"
            line="301"
            column="21"/>
    </issue>

    <issue
        id="DefaultLocale"
        message="Implicitly using the default locale is a common source of bugs: Use `String.format(Locale, ...)` instead"
        errorLine1="                        logInfo(String.format("
        errorLine2="                                ^">
        <location
            file="src/main/java/com/northcoders/pigliotech_frontend/utils/BackendStatusManager.java"
            line="319"
            column="33"/>
    </issue>

    <issue
        id="DefaultLocale"
        message="Implicitly using the default locale is a common source of bugs: Use `String.format(Locale, ...)` instead"
        errorLine1="                            logWarning(String.format("
        errorLine2="                                       ^">
        <location
            file="src/main/java/com/northcoders/pigliotech_frontend/utils/BackendStatusManager.java"
            line="326"
            column="40"/>
    </issue>

    <issue
        id="DefaultLocale"
        message="Implicitly using the default locale is a common source of bugs: Use `String.format(Locale, ...)` instead"
        errorLine1="                                String.format(&quot;Ping failed: %s - Response time: %d ms - User wait time: %d min %d sec&quot;,"
        errorLine2="                                ^">
        <location
            file="src/main/java/com/northcoders/pigliotech_frontend/utils/BackendStatusManager.java"
            line="343"
            column="33"/>
    </issue>

    <issue
        id="DefaultLocale"
        message="Implicitly using the default locale is a common source of bugs: Use `String.format(Locale, ...)` instead"
        errorLine1="                logDebug(String.format(&quot;Waiting %d ms before next retry (attempt %d/%d)&quot;,"
        errorLine2="                         ^">
        <location
            file="src/main/java/com/northcoders/pigliotech_frontend/utils/BackendStatusManager.java"
            line="382"
            column="26"/>
    </issue>

    <issue
        id="DefaultLocale"
        message="Implicitly using the default locale is a common source of bugs: Use `String.format(Locale, ...)` instead"
        errorLine1="            logInfo(String.format(&quot;Pinging backend (attempt %d/%d) - User wait time: %d min %d sec&quot;,"
        errorLine2="                    ^">
        <location
            file="src/main/java/com/northcoders/pigliotech_frontend/utils/BackendStatusManager.java"
            line="395"
            column="21"/>
    </issue>

    <issue
        id="DefaultLocale"
        message="Implicitly using the default locale is a common source of bugs: Use `String.format(Locale, ...)` instead"
        errorLine1="                            logInfo(String.format("
        errorLine2="                                    ^">
        <location
            file="src/main/java/com/northcoders/pigliotech_frontend/utils/BackendStatusManager.java"
            line="412"
            column="37"/>
    </issue>

    <issue
        id="DefaultLocale"
        message="Implicitly using the default locale is a common source of bugs: Use `String.format(Locale, ...)` instead"
        errorLine1="                            logWarning(String.format("
        errorLine2="                                       ^">
        <location
            file="src/main/java/com/northcoders/pigliotech_frontend/utils/BackendStatusManager.java"
            line="417"
            column="40"/>
    </issue>

    <issue
        id="DefaultLocale"
        message="Implicitly using the default locale is a common source of bugs: Use `String.format(Locale, ...)` instead"
        errorLine1="                                String.format(&quot;Ping failed: %s - Response time: %d ms - User wait time: %d min %d sec&quot;,"
        errorLine2="                                ^">
        <location
            file="src/main/java/com/northcoders/pigliotech_frontend/utils/BackendStatusManager.java"
            line="429"
            column="33"/>
    </issue>

    <issue
        id="DefaultLocale"
        message="Implicitly using the default locale is a common source of bugs: Use `String.format(Locale, ...)` instead"
        errorLine1="                        logWarning(String.format(&quot;Ping failed (attempt %d/%d) - Elapsed time: %d min %d sec&quot;,"
        errorLine2="                                   ^">
        <location
            file="src/main/java/com/northcoders/pigliotech_frontend/utils/BackendStatusManager.java"
            line="528"
            column="36"/>
    </issue>

    <issue
        id="DefaultLocale"
        message="Implicitly using the default locale is a common source of bugs: Use `String.format(Locale, ...)` instead"
        errorLine1="                        logInfo(String.format(&quot;Google ping successful - Response time: %d ms&quot;, responseTimeMs));"
        errorLine2="                                ~~~~~~~~~~~~~~~~~~~~~~~~~~~~~~~~~~~~~~~~~~~~~~~~~~~~~~~~~~~~~~~~~~~~~~~~~~~~~~">
        <location
            file="src/main/java/com/northcoders/pigliotech_frontend/utils/BackendStatusManager.java"
            line="596"
            column="33"/>
    </issue>

    <issue
        id="DefaultLocale"
        message="Implicitly using the default locale is a common source of bugs: Use `String.format(Locale, ...)` instead"
        errorLine1="                        logWarning(String.format(&quot;Google ping failed with code: %d - Response time: %d ms&quot;,"
        errorLine2="                                   ^">
        <location
            file="src/main/java/com/northcoders/pigliotech_frontend/utils/BackendStatusManager.java"
            line="600"
            column="36"/>
    </issue>

    <issue
        id="DefaultLocale"
        message="Implicitly using the default locale is a common source of bugs: Use `String.format(Locale, ...)` instead"
        errorLine1="                    logWarning(String.format(&quot;Google ping failed: %s - Response time: %d ms&quot;,"
        errorLine2="                               ^">
        <location
            file="src/main/java/com/northcoders/pigliotech_frontend/utils/BackendStatusManager.java"
            line="610"
            column="32"/>
    </issue>

    <issue
        id="DefaultLocale"
        message="Implicitly using the default locale is a common source of bugs: Use `String.format(Locale, ...)` instead"
        errorLine1="                String message = String.format("
        errorLine2="                                 ^">
        <location
            file="src/main/java/com/northcoders/pigliotech_frontend/utils/BackendStatusManager.java"
            line="667"
            column="34"/>
    </issue>

    <issue
        id="DefaultLocale"
        message="Implicitly using the default locale is a common source of bugs: Use `String.format(Locale, ...)` instead"
        errorLine1="        return String.format(&quot;[Status: %s, Retry: %d/%d, Elapsed: %ds]&quot;,"
        errorLine2="               ^">
        <location
            file="src/main/java/com/northcoders/pigliotech_frontend/utils/BackendStatusManager.java"
            line="755"
            column="16"/>
    </issue>

    <issue
        id="InlinedApi"
        message="Field requires API level 33 (current min is 24): `android.content.Context#RECEIVER_NOT_EXPORTED`"
        errorLine1="            registerReceiver(backendOnlineReceiver, filter, Context.RECEIVER_NOT_EXPORTED);"
        errorLine2="                                                            ~~~~~~~~~~~~~~~~~~~~~~~~~~~~~">
        <location
            file="src/main/java/com/northcoders/pigliotech_frontend/activities/BackendColdStartActivity.java"
            line="131"
            column="61"/>
    </issue>

    <issue
        id="NewApi"
        message="Call requires API level 26 (current min is 24): `android.content.ContextWrapper#registerReceiver`"
        errorLine1="            registerReceiver(backendOnlineReceiver, filter, Context.RECEIVER_NOT_EXPORTED);"
        errorLine2="            ~~~~~~~~~~~~~~~~">
        <location
            file="src/main/java/com/northcoders/pigliotech_frontend/activities/BackendColdStartActivity.java"
            line="131"
            column="13"/>
    </issue>

    <issue
        id="OldTargetApi"
        message="Not targeting the latest versions of Android; compatibility modes apply. Consider testing and updating this version. Consult the `android.os.Build.VERSION_CODES` javadoc for details."
        errorLine1="        targetSdk 34"
        errorLine2="        ~~~~~~~~~~~~">
        <location
            file="build.gradle"
            line="13"
            column="9"/>
    </issue>

    <issue
        id="SimpleDateFormat"
        message="To get local formatting use `getDateInstance()`, `getDateTimeInstance()`, or `getTimeInstance()`, or use `new SimpleDateFormat(String template, Locale locale)` with for example `Locale.US` for ASCII dates."
        errorLine1="                        new java.text.SimpleDateFormat(&quot;HH:mm:ss.SSS&quot;).format(new java.util.Date(nextRetryTime))));"
        errorLine2="                        ~~~~~~~~~~~~~~~~~~~~~~~~~~~~~~~~~~~~~~~~~~~~~~">
        <location
            file="src/main/java/com/northcoders/pigliotech_frontend/utils/BackendStatusManager.java"
            line="192"
            column="25"/>
    </issue>

    <issue
        id="UnspecifiedRegisterReceiverFlag"
        message="`backendOnlineReceiver` is missing `RECEIVER_EXPORTED` or `RECEIVER_NOT_EXPORTED` flag for unprotected broadcasts registered for com.northcoders.pigliotech_frontend.BACKEND_ONLINE"
        errorLine1="        registerReceiver(backendOnlineReceiver, filter);"
        errorLine2="        ~~~~~~~~~~~~~~~~~~~~~~~~~~~~~~~~~~~~~~~~~~~~~~~">
        <location
            file="src/main/java/com/northcoders/pigliotech_frontend/activities/BackendColdStartActivity.java"
            line="201"
            column="9"/>
    </issue>

    <issue
        id="AndroidGradlePluginVersion"
        message="A newer version of com.android.application than 8.8.0 is available: 8.9.1. (There is also a newer version of 8.8.ð‘¥ available, if upgrading to 8.9.1 is difficult: 8.8.2)"
        errorLine1="agp = &quot;8.8.0&quot;"
        errorLine2="      ~~~~~~~">
        <location
            file="$HOME/Northcoders/jv-group-project/PiglioTech-FrontEnd/gradle/libs.versions.toml"
            line="2"
            column="7"/>
    </issue>

    <issue
        id="AndroidGradlePluginVersion"
        message="A newer version of com.android.application than 8.8.0 is available: 8.9.1. (There is also a newer version of 8.8.ð‘¥ available, if upgrading to 8.9.1 is difficult: 8.8.2)"
        errorLine1="agp = &quot;8.8.0&quot;"
        errorLine2="      ~~~~~~~">
        <location
            file="$HOME/Northcoders/jv-group-project/PiglioTech-FrontEnd/gradle/libs.versions.toml"
            line="2"
            column="7"/>
    </issue>

    <issue
        id="AndroidGradlePluginVersion"
        message="A newer version of com.android.application than 8.8.0 is available: 8.9.1. (There is also a newer version of 8.8.ð‘¥ available, if upgrading to 8.9.1 is difficult: 8.8.2)"
        errorLine1="agp = &quot;8.8.0&quot;"
        errorLine2="      ~~~~~~~">
        <location
            file="$HOME/Northcoders/jv-group-project/PiglioTech-FrontEnd/gradle/libs.versions.toml"
            line="2"
            column="7"/>
    </issue>

    <issue
        id="GradleDependency"
        message="A newer version of androidx.appcompat:appcompat than 1.1.0 is available: 1.7.0"
        errorLine1="appcompatVersion = &quot;1.1.0&quot;"
        errorLine2="                   ~~~~~~~">
        <location
            file="$HOME/Northcoders/jv-group-project/PiglioTech-FrontEnd/gradle/libs.versions.toml"
            line="3"
            column="20"/>
    </issue>

    <issue
        id="GradleDependency"
        message="A newer version of androidx.appcompat:appcompat than 1.1.0 is available: 1.7.0"
        errorLine1="appcompatVersion = &quot;1.1.0&quot;"
        errorLine2="                   ~~~~~~~">
        <location
            file="$HOME/Northcoders/jv-group-project/PiglioTech-FrontEnd/gradle/libs.versions.toml"
            line="3"
            column="20"/>
    </issue>

    <issue
        id="GradleDependency"
        message="A newer version of androidx.appcompat:appcompat than 1.1.0 is available: 1.7.0"
        errorLine1="appcompatVersion = &quot;1.1.0&quot;"
        errorLine2="                   ~~~~~~~">
        <location
            file="$HOME/Northcoders/jv-group-project/PiglioTech-FrontEnd/gradle/libs.versions.toml"
            line="3"
            column="20"/>
    </issue>

    <issue
        id="GradleDependency"
        message="A newer version of com.google.firebase:firebase-bom than 33.7.0 is available: 33.12.0"
        errorLine1="firebaseBom = &quot;33.7.0&quot;"
        errorLine2="              ~~~~~~~~">
        <location
            file="$HOME/Northcoders/jv-group-project/PiglioTech-FrontEnd/gradle/libs.versions.toml"
            line="5"
            column="15"/>
    </issue>

    <issue
        id="GradleDependency"
        message="A newer version of com.google.firebase:firebase-bom than 33.7.0 is available: 33.12.0"
        errorLine1="firebaseBom = &quot;33.7.0&quot;"
        errorLine2="              ~~~~~~~~">
        <location
            file="$HOME/Northcoders/jv-group-project/PiglioTech-FrontEnd/gradle/libs.versions.toml"
            line="5"
            column="15"/>
    </issue>

    <issue
        id="GradleDependency"
        message="A newer version of com.google.firebase:firebase-bom than 33.7.0 is available: 33.12.0"
        errorLine1="firebaseBom = &quot;33.7.0&quot;"
        errorLine2="              ~~~~~~~~">
        <location
            file="$HOME/Northcoders/jv-group-project/PiglioTech-FrontEnd/gradle/libs.versions.toml"
            line="5"
            column="15"/>
    </issue>

    <issue
        id="GradleDependency"
        message="A newer version of com.squareup.okhttp3:logging-interceptor than 3.4.1 is available: 4.12.0"
        errorLine1="loggingInterceptor = &quot;3.4.1&quot;"
        errorLine2="                     ~~~~~~~">
        <location
            file="$HOME/Northcoders/jv-group-project/PiglioTech-FrontEnd/gradle/libs.versions.toml"
            line="11"
            column="22"/>
    </issue>

    <issue
        id="GradleDependency"
        message="A newer version of com.squareup.okhttp3:logging-interceptor than 3.4.1 is available: 4.12.0"
        errorLine1="loggingInterceptor = &quot;3.4.1&quot;"
        errorLine2="                     ~~~~~~~">
        <location
            file="$HOME/Northcoders/jv-group-project/PiglioTech-FrontEnd/gradle/libs.versions.toml"
            line="11"
            column="22"/>
    </issue>

    <issue
        id="GradleDependency"
        message="A newer version of com.squareup.okhttp3:logging-interceptor than 3.4.1 is available: 4.12.0"
        errorLine1="loggingInterceptor = &quot;3.4.1&quot;"
        errorLine2="                     ~~~~~~~">
        <location
            file="$HOME/Northcoders/jv-group-project/PiglioTech-FrontEnd/gradle/libs.versions.toml"
            line="11"
            column="22"/>
    </issue>

    <issue
        id="GradleDependency"
        message="A newer version of androidx.activity:activity than 1.9.3 is available: 1.10.1"
        errorLine1="activity = &quot;1.9.3&quot;"
        errorLine2="           ~~~~~~~">
        <location
            file="$HOME/Northcoders/jv-group-project/PiglioTech-FrontEnd/gradle/libs.versions.toml"
            line="13"
            column="12"/>
    </issue>

    <issue
        id="GradleDependency"
        message="A newer version of androidx.activity:activity than 1.9.3 is available: 1.10.1"
        errorLine1="activity = &quot;1.9.3&quot;"
        errorLine2="           ~~~~~~~">
        <location
            file="$HOME/Northcoders/jv-group-project/PiglioTech-FrontEnd/gradle/libs.versions.toml"
            line="13"
            column="12"/>
    </issue>

    <issue
        id="GradleDependency"
        message="A newer version of androidx.activity:activity than 1.9.3 is available: 1.10.1"
        errorLine1="activity = &quot;1.9.3&quot;"
        errorLine2="           ~~~~~~~">
        <location
            file="$HOME/Northcoders/jv-group-project/PiglioTech-FrontEnd/gradle/libs.versions.toml"
            line="13"
            column="12"/>
    </issue>

    <issue
        id="GradleDependency"
        message="A newer version of androidx.constraintlayout:constraintlayout than 2.2.0 is available: 2.2.1"
        errorLine1="constraintlayout = &quot;2.2.0&quot;"
        errorLine2="                   ~~~~~~~">
        <location
            file="$HOME/Northcoders/jv-group-project/PiglioTech-FrontEnd/gradle/libs.versions.toml"
            line="14"
            column="20"/>
    </issue>

    <issue
        id="GradleDependency"
        message="A newer version of androidx.constraintlayout:constraintlayout than 2.2.0 is available: 2.2.1"
        errorLine1="constraintlayout = &quot;2.2.0&quot;"
        errorLine2="                   ~~~~~~~">
        <location
            file="$HOME/Northcoders/jv-group-project/PiglioTech-FrontEnd/gradle/libs.versions.toml"
            line="14"
            column="20"/>
    </issue>

    <issue
        id="GradleDependency"
        message="A newer version of androidx.constraintlayout:constraintlayout than 2.2.0 is available: 2.2.1"
        errorLine1="constraintlayout = &quot;2.2.0&quot;"
        errorLine2="                   ~~~~~~~">
        <location
            file="$HOME/Northcoders/jv-group-project/PiglioTech-FrontEnd/gradle/libs.versions.toml"
            line="14"
            column="20"/>
    </issue>

    <issue
        id="GradleDependency"
        message="A newer version of com.google.android.material:material than 1.0.0 is available: 1.12.0"
        errorLine1="materialVersion = &quot;1.0.0&quot;"
        errorLine2="                  ~~~~~~~">
        <location
            file="$HOME/Northcoders/jv-group-project/PiglioTech-FrontEnd/gradle/libs.versions.toml"
            line="15"
            column="19"/>
    </issue>

    <issue
        id="GradleDependency"
        message="A newer version of com.google.android.material:material than 1.0.0 is available: 1.12.0"
        errorLine1="materialVersion = &quot;1.0.0&quot;"
        errorLine2="                  ~~~~~~~">
        <location
            file="$HOME/Northcoders/jv-group-project/PiglioTech-FrontEnd/gradle/libs.versions.toml"
            line="15"
            column="19"/>
    </issue>

    <issue
        id="GradleDependency"
        message="A newer version of com.google.android.material:material than 1.0.0 is available: 1.12.0"
        errorLine1="materialVersion = &quot;1.0.0&quot;"
        errorLine2="                  ~~~~~~~">
        <location
            file="$HOME/Northcoders/jv-group-project/PiglioTech-FrontEnd/gradle/libs.versions.toml"
            line="15"
            column="19"/>
    </issue>

    <issue
        id="SimilarGradleDependency"
        message="There are multiple dependencies androidx.appcompat:appcompat but with different version"
        errorLine1="appcompat-v110 = { module = &quot;androidx.appcompat:appcompat&quot;, version.ref = &quot;appcompatVersion&quot; }"
        errorLine2="                  ~~~~~~~~~~~~~~~~~~~~~~~~~~~~~~~~~~~~~~~~~~~~~~~~~~~~~~~~~~~~~~~~~~~~~~~~~~~~">
        <location
            file="$HOME/Northcoders/jv-group-project/PiglioTech-FrontEnd/gradle/libs.versions.toml"
            line="20"
            column="19"/>
    </issue>

    <issue
        id="SimilarGradleDependency"
        message="There are multiple dependencies androidx.appcompat:appcompat but with different version"
        errorLine1="appcompat-v110 = { module = &quot;androidx.appcompat:appcompat&quot;, version.ref = &quot;appcompatVersion&quot; }"
        errorLine2="                  ~~~~~~~~~~~~~~~~~~~~~~~~~~~~~~~~~~~~~~~~~~~~~~~~~~~~~~~~~~~~~~~~~~~~~~~~~~~~">
        <location
            file="$HOME/Northcoders/jv-group-project/PiglioTech-FrontEnd/gradle/libs.versions.toml"
            line="20"
            column="19"/>
    </issue>

    <issue
        id="SimilarGradleDependency"
        message="There are multiple dependencies androidx.appcompat:appcompat but with different version"
        errorLine1="appcompat-v110 = { module = &quot;androidx.appcompat:appcompat&quot;, version.ref = &quot;appcompatVersion&quot; }"
        errorLine2="                  ~~~~~~~~~~~~~~~~~~~~~~~~~~~~~~~~~~~~~~~~~~~~~~~~~~~~~~~~~~~~~~~~~~~~~~~~~~~~">
        <location
            file="$HOME/Northcoders/jv-group-project/PiglioTech-FrontEnd/gradle/libs.versions.toml"
            line="20"
            column="19"/>
    </issue>

    <issue
        id="SimilarGradleDependency"
        message="There are multiple dependencies androidx.appcompat:appcompat but with different version"
        errorLine1="appcompat = { group = &quot;androidx.appcompat&quot;, name = &quot;appcompat&quot;, version.ref = &quot;appcompat&quot; }"
        errorLine2="             ~~~~~~~~~~~~~~~~~~~~~~~~~~~~~~~~~~~~~~~~~~~~~~~~~~~~~~~~~~~~~~~~~~~~~~~~~~~~~~">
        <location
            file="$HOME/Northcoders/jv-group-project/PiglioTech-FrontEnd/gradle/libs.versions.toml"
            line="28"
            column="14"/>
    </issue>

    <issue
        id="SimilarGradleDependency"
        message="There are multiple dependencies androidx.appcompat:appcompat but with different version"
        errorLine1="appcompat = { group = &quot;androidx.appcompat&quot;, name = &quot;appcompat&quot;, version.ref = &quot;appcompat&quot; }"
        errorLine2="             ~~~~~~~~~~~~~~~~~~~~~~~~~~~~~~~~~~~~~~~~~~~~~~~~~~~~~~~~~~~~~~~~~~~~~~~~~~~~~~">
        <location
            file="$HOME/Northcoders/jv-group-project/PiglioTech-FrontEnd/gradle/libs.versions.toml"
            line="28"
            column="14"/>
    </issue>

    <issue
        id="SimilarGradleDependency"
        message="There are multiple dependencies androidx.appcompat:appcompat but with different version"
        errorLine1="appcompat = { group = &quot;androidx.appcompat&quot;, name = &quot;appcompat&quot;, version.ref = &quot;appcompat&quot; }"
        errorLine2="             ~~~~~~~~~~~~~~~~~~~~~~~~~~~~~~~~~~~~~~~~~~~~~~~~~~~~~~~~~~~~~~~~~~~~~~~~~~~~~~">
        <location
            file="$HOME/Northcoders/jv-group-project/PiglioTech-FrontEnd/gradle/libs.versions.toml"
            line="28"
            column="14"/>
    </issue>

    <issue
        id="SimilarGradleDependency"
        message="There are multiple dependencies com.google.android.material:material but with different version"
        errorLine1="material = { group = &quot;com.google.android.material&quot;, name = &quot;material&quot;, version.ref = &quot;material&quot; }"
        errorLine2="            ~~~~~~~~~~~~~~~~~~~~~~~~~~~~~~~~~~~~~~~~~~~~~~~~~~~~~~~~~~~~~~~~~~~~~~~~~~~~~~~~~~~~~">
        <location
            file="$HOME/Northcoders/jv-group-project/PiglioTech-FrontEnd/gradle/libs.versions.toml"
            line="30"
            column="13"/>
    </issue>

    <issue
        id="SimilarGradleDependency"
        message="There are multiple dependencies com.google.android.material:material but with different version"
        errorLine1="material = { group = &quot;com.google.android.material&quot;, name = &quot;material&quot;, version.ref = &quot;material&quot; }"
        errorLine2="            ~~~~~~~~~~~~~~~~~~~~~~~~~~~~~~~~~~~~~~~~~~~~~~~~~~~~~~~~~~~~~~~~~~~~~~~~~~~~~~~~~~~~~">
        <location
            file="$HOME/Northcoders/jv-group-project/PiglioTech-FrontEnd/gradle/libs.versions.toml"
            line="30"
            column="13"/>
    </issue>

    <issue
        id="SimilarGradleDependency"
        message="There are multiple dependencies com.google.android.material:material but with different version"
        errorLine1="material = { group = &quot;com.google.android.material&quot;, name = &quot;material&quot;, version.ref = &quot;material&quot; }"
        errorLine2="            ~~~~~~~~~~~~~~~~~~~~~~~~~~~~~~~~~~~~~~~~~~~~~~~~~~~~~~~~~~~~~~~~~~~~~~~~~~~~~~~~~~~~~">
        <location
            file="$HOME/Northcoders/jv-group-project/PiglioTech-FrontEnd/gradle/libs.versions.toml"
            line="30"
            column="13"/>
    </issue>

    <issue
        id="SimilarGradleDependency"
        message="There are multiple dependencies com.google.android.material:material but with different version"
        errorLine1="material-v100 = { module = &quot;com.google.android.material:material&quot;, version.ref = &quot;materialVersion&quot; }"
        errorLine2="                 ~~~~~~~~~~~~~~~~~~~~~~~~~~~~~~~~~~~~~~~~~~~~~~~~~~~~~~~~~~~~~~~~~~~~~~~~~~~~~~~~~~~">
        <location
            file="$HOME/Northcoders/jv-group-project/PiglioTech-FrontEnd/gradle/libs.versions.toml"
            line="33"
            column="18"/>
    </issue>

    <issue
        id="SimilarGradleDependency"
        message="There are multiple dependencies com.google.android.material:material but with different version"
        errorLine1="material-v100 = { module = &quot;com.google.android.material:material&quot;, version.ref = &quot;materialVersion&quot; }"
        errorLine2="                 ~~~~~~~~~~~~~~~~~~~~~~~~~~~~~~~~~~~~~~~~~~~~~~~~~~~~~~~~~~~~~~~~~~~~~~~~~~~~~~~~~~~">
        <location
            file="$HOME/Northcoders/jv-group-project/PiglioTech-FrontEnd/gradle/libs.versions.toml"
            line="33"
            column="18"/>
    </issue>

    <issue
        id="SimilarGradleDependency"
        message="There are multiple dependencies com.google.android.material:material but with different version"
        errorLine1="material-v100 = { module = &quot;com.google.android.material:material&quot;, version.ref = &quot;materialVersion&quot; }"
        errorLine2="                 ~~~~~~~~~~~~~~~~~~~~~~~~~~~~~~~~~~~~~~~~~~~~~~~~~~~~~~~~~~~~~~~~~~~~~~~~~~~~~~~~~~~">
        <location
            file="$HOME/Northcoders/jv-group-project/PiglioTech-FrontEnd/gradle/libs.versions.toml"
            line="33"
            column="18"/>
    </issue>

    <issue
        id="NotifyDataSetChanged"
        message="It will always be more efficient to use more specific change events if you can. Rely on `notifyDataSetChanged` as a last resort."
        errorLine1="        userAdapter.notifyDataSetChanged();"
        errorLine2="        ~~~~~~~~~~~~~~~~~~~~~~~~~~~~~~~~~~">
        <location
            file="src/main/java/com/northcoders/pigliotech_frontend/ui/fragments/profile/ProfileFragment.java"
            line="182"
            column="9"/>
    </issue>

    <issue
        id="NotifyDataSetChanged"
        message="It will always be more efficient to use more specific change events if you can. Rely on `notifyDataSetChanged` as a last resort."
        errorLine1="        swapAdapter.notifyDataSetChanged();"
        errorLine2="        ~~~~~~~~~~~~~~~~~~~~~~~~~~~~~~~~~~">
        <location
            file="src/main/java/com/northcoders/pigliotech_frontend/ui/fragments/swapbook/SwapFragment.java"
            line="120"
            column="9"/>
    </issue>

    <issue
        id="StaticFieldLeak"
        message="Do not place Android context classes in static fields; this is a memory leak"
        errorLine1="    private static Context context;"
        errorLine2="            ~~~~~~">
        <location
            file="src/main/java/com/northcoders/pigliotech_frontend/PiglioTechApp.java"
            line="7"
            column="13"/>
    </issue>

    <issue
        id="Overdraw"
        message="Possible overdraw: Root element paints background `@color/white` with a theme that also paints a background (inferred theme is `@style/Theme_AppCompat_Light_NoActionBar`)"
        errorLine1="    android:background=&quot;@color/white&quot;"
        errorLine2="    ~~~~~~~~~~~~~~~~~~~~~~~~~~~~~~~~~">
        <location
            file="src/main/res/layout/activity_backend_cold_start.xml"
            line="7"
            column="5"/>
    </issue>

    <issue
        id="UnusedResources"
        message="The resource `R.drawable.ic_accept` appears to be unused"
        errorLine1="&lt;vector xmlns:android=&quot;http://schemas.android.com/apk/res/android&quot; android:height=&quot;48dp&quot; android:tint=&quot;#FFFFFF&quot; android:viewportHeight=&quot;24&quot; android:viewportWidth=&quot;24&quot; android:width=&quot;48dp&quot;>"
        errorLine2="^">
        <location
            file="src/main/res/drawable/ic_accept.xml"
            line="1"
            column="1"/>
    </issue>

    <issue
        id="UnusedResources"
        message="The resource `R.drawable.ic_launcher_foreground` appears to be unused"
        errorLine1="&lt;vector xmlns:android=&quot;http://schemas.android.com/apk/res/android&quot;"
        errorLine2="^">
        <location
            file="src/main/res/drawable/ic_launcher_foreground.xml"
            line="1"
            column="1"/>
    </issue>

    <issue
        id="UnusedResources"
        message="The resource `R.string.hello_blank_fragment` appears to be unused"
        errorLine1="    &lt;string name=&quot;hello_blank_fragment&quot;>Hello blank fragment&lt;/string>"
        errorLine2="            ~~~~~~~~~~~~~~~~~~~~~~~~~~~">
        <location
            file="src/main/res/values/strings.xml"
            line="3"
            column="13"/>
    </issue>

    <issue
        id="UnusedResources"
        message="The resource `R.drawable.swap_decline_button` appears to be unused"
        errorLine1="&lt;shape xmlns:android=&quot;http://schemas.android.com/apk/res/android&quot;>"
        errorLine2="^">
        <location
            file="src/main/res/drawable/swap_decline_button.xml"
            line="2"
            column="1"/>
    </issue>

    <issue
        id="MonochromeLauncherIcon"
        message="The application adaptive icon is missing a monochrome tag"
        errorLine1="&lt;adaptive-icon xmlns:android=&quot;http://schemas.android.com/apk/res/android&quot;>"
        errorLine2="^">
        <location
            file="src/main/res/mipmap-anydpi-v26/ic_launcher.xml"
            line="2"
            column="1"/>
    </issue>

    <issue
        id="MonochromeLauncherIcon"
        message="The application adaptive roundIcon is missing a monochrome tag"
        errorLine1="&lt;adaptive-icon xmlns:android=&quot;http://schemas.android.com/apk/res/android&quot;>"
        errorLine2="^">
        <location
            file="src/main/res/mipmap-anydpi-v26/ic_launcher_round.xml"
            line="2"
            column="1"/>
    </issue>

    <issue
        id="IconLocation"
        message="Found bitmap drawable `res/drawable/blank_book.jpg` in densityless folder">
        <location
            file="src/main/res/drawable/blank_book.jpg"/>
    </issue>

    <issue
        id="IconLocation"
        message="Found bitmap drawable `res/drawable/blank_pfp.webp` in densityless folder">
        <location
            file="src/main/res/drawable/blank_pfp.webp"/>
    </issue>

    <issue
        id="IconLocation"
        message="Found bitmap drawable `res/drawable/home_background.png` in densityless folder">
        <location
            file="src/main/res/drawable/home_background.png"/>
    </issue>

    <issue
        id="IconLocation"
        message="Found bitmap drawable `res/drawable/landing_background.png` in densityless folder">
        <location
            file="src/main/res/drawable/landing_background.png"/>
    </issue>

    <issue
        id="TextFields"
        message="This text field does not specify an `inputType`"
        errorLine1="        &lt;EditText"
        errorLine2="         ~~~~~~~~">
        <location
            file="src/main/res/layout/fragment_add_book.xml"
            line="42"
            column="10"/>
    </issue>

    <issue
        id="Autofill"
        message="Missing `autofillHints` attribute"
        errorLine1="        &lt;EditText"
        errorLine2="         ~~~~~~~~">
        <location
            file="src/main/res/layout/fragment_add_book.xml"
            line="42"
            column="10"/>
    </issue>

    <issue
        id="Autofill"
        message="Missing `autofillHints` attribute"
        errorLine1="            &lt;EditText"
        errorLine2="             ~~~~~~~~">
        <location
            file="src/main/res/layout/fragment_login.xml"
            line="51"
            column="14"/>
    </issue>

    <issue
        id="Autofill"
        message="Missing `autofillHints` attribute"
        errorLine1="            &lt;EditText"
        errorLine2="             ~~~~~~~~">
        <location
            file="src/main/res/layout/fragment_login.xml"
            line="79"
            column="14"/>
    </issue>

    <issue
        id="Autofill"
        message="Missing `autofillHints` attribute"
        errorLine1="            &lt;EditText"
        errorLine2="             ~~~~~~~~">
        <location
            file="src/main/res/layout/fragment_sign_up.xml"
            line="68"
            column="14"/>
    </issue>

    <issue
        id="Autofill"
        message="Missing `autofillHints` attribute"
        errorLine1="            &lt;EditText"
        errorLine2="             ~~~~~~~~">
        <location
            file="src/main/res/layout/fragment_sign_up.xml"
            line="92"
            column="14"/>
    </issue>

    <issue
        id="Autofill"
        message="Missing `autofillHints` attribute"
        errorLine1="            &lt;EditText"
        errorLine2="             ~~~~~~~~">
        <location
            file="src/main/res/layout/fragment_sign_up.xml"
            line="115"
            column="14"/>
    </issue>

    <issue
        id="ContentDescription"
        message="Missing `contentDescription` attribute on image"
        errorLine1="    &lt;ImageView"
        errorLine2="     ~~~~~~~~~">
        <location
            file="src/main/res/layout/activity_backend_cold_start.xml"
            line="10"
            column="6"/>
    </issue>

    <issue
        id="ContentDescription"
        message="Missing `contentDescription` attribute on image"
        errorLine1="        &lt;ImageView"
        errorLine2="         ~~~~~~~~~">
        <location
            file="src/main/res/layout/library_view.xml"
            line="27"
            column="10"/>
    </issue>

    <issue
        id="SetTextI18n"
        message="Do not concatenate text displayed with `setText`. Use resource string with placeholders."
        errorLine1="                    &quot;Our backend server is currently starting up. This is normal for development environments and may take up to 30 minutes if the server hasn&apos;t been used recently.\n\n&quot;"
        errorLine2="                    ^">
        <location
            file="src/main/java/com/northcoders/pigliotech_frontend/activities/BackendColdStartActivity.java"
            line="73"
            column="21"/>
    </issue>

    <issue
        id="SetTextI18n"
        message="String literal in `setText` can not be translated. Use Android resources instead."
        errorLine1="                            &quot;You don&apos;t need to keep clicking &apos;Try Again&apos; - the app will automatically detect when the server is back online and continue.&quot;);"
        errorLine2="                            ~~~~~~~~~~~~~~~~~~~~~~~~~~~~~~~~~~~~~~~~~~~~~~~~~~~~~~~~~~~~~~~~~~~~~~~~~~~~~~~~~~~~~~~~~~~~~~~~~~~~~~~~~~~~~~~~~~~~~~~~~~~~~~">
        <location
            file="src/main/java/com/northcoders/pigliotech_frontend/activities/BackendColdStartActivity.java"
            line="77"
            column="29"/>
    </issue>

    <issue
        id="HardcodedText"
        message="Hardcoded string &quot;Backend is Starting Up&quot;, should use `@string` resource"
        errorLine1="        android:text=&quot;Backend is Starting Up&quot;"
        errorLine2="        ~~~~~~~~~~~~~~~~~~~~~~~~~~~~~~~~~~~~~">
        <location
            file="src/main/res/layout/activity_backend_cold_start.xml"
            line="26"
            column="9"/>
    </issue>

    <issue
        id="HardcodedText"
        message="Hardcoded string &quot;Time elapsed: 0 min 0 sec&quot;, should use `@string` resource"
        errorLine1="        android:text=&quot;Time elapsed: 0 min 0 sec&quot;"
        errorLine2="        ~~~~~~~~~~~~~~~~~~~~~~~~~~~~~~~~~~~~~~~~">
        <location
            file="src/main/res/layout/activity_backend_cold_start.xml"
            line="40"
            column="9"/>
    </issue>

    <issue
        id="HardcodedText"
        message="Hardcoded string &quot;Our backend server is currently starting up. This is normal for development environments and may take up to 10 minutes if the server hasn&apos;t been used recently.\n\nThis happens because we&apos;re using a free tier on Render.com which puts our server to sleep after periods of inactivity to save resources.\n\nYou don&apos;t need to keep clicking &apos;Try Again&apos; - the app will automatically detect when the server is back online and continue.&quot;, should use `@string` resource"
        errorLine1="        android:text=&quot;Our backend server is currently starting up. This is normal for development environments and may take up to 10 minutes if the server hasn&apos;t been used recently.\n\nThis happens because we&apos;re using a free tier on Render.com which puts our server to sleep after periods of inactivity to save resources.\n\nYou don&apos;t need to keep clicking &apos;Try Again&apos; - the app will automatically detect when the server is back online and continue.&quot;"
        errorLine2="        ~~~~~~~~~~~~~~~~~~~~~~~~~~~~~~~~~~~~~~~~~~~~~~~~~~~~~~~~~~~~~~~~~~~~~~~~~~~~~~~~~~~~~~~~~~~~~~~~~~~~~~~~~~~~~~~~~~~~~~~~~~~~~~~~~~~~~~~~~~~~~~~~~~~~~~~~~~~~~~~~~~~~~~~~~~~~~~~~~~~~~~~~~~~~~~~~~~~~~~~~~~~~~~~~~~~~~~~~~~~~~~~~~~~~~~~~~~~~~~~~~~~~~~~~~~~~~~~~~~~~~~~~~~~~~~~~~~~~~~~~~~~~~~~~~~~~~~~~~~~~~~~~~~~~~~~~~~~~~~~~~~~~~~~~~~~~~~~~~~~~~~~~~~~~~~~~~~~~~~~~~~~~~~~~~~~~~~~~~~~~~~~~~~~~~~~~~~~~~~~~~~~~~~~~~~~~~~~~~~~~~~~~~~~~~~~~~~~~~~~~~~">
        <location
            file="src/main/res/layout/activity_backend_cold_start.xml"
            line="57"
            column="9"/>
    </issue>

    <issue
        id="HardcodedText"
        message="Hardcoded string &quot;Try Again&quot;, should use `@string` resource"
        errorLine1="        android:text=&quot;Try Again&quot;"
        errorLine2="        ~~~~~~~~~~~~~~~~~~~~~~~~">
        <location
            file="src/main/res/layout/activity_backend_cold_start.xml"
            line="74"
            column="9"/>
    </issue>

    <issue
        id="HardcodedText"
        message="Hardcoded string &quot;Home&quot;, should use `@string` resource"
        errorLine1="        android:title=&quot;Home&quot;"
        errorLine2="        ~~~~~~~~~~~~~~~~~~~~">
        <location
            file="src/main/res/menu/bottom_nav_menu.xml"
            line="5"
            column="9"/>
    </issue>

    <issue
        id="HardcodedText"
        message="Hardcoded string &quot;Exchange&quot;, should use `@string` resource"
        errorLine1="        android:title=&quot;Exchange&quot;"
        errorLine2="        ~~~~~~~~~~~~~~~~~~~~~~~~">
        <location
            file="src/main/res/menu/bottom_nav_menu.xml"
            line="10"
            column="9"/>
    </issue>

    <issue
        id="HardcodedText"
        message="Hardcoded string &quot;Profile&quot;, should use `@string` resource"
        errorLine1="        android:title=&quot;Profile&quot;"
        errorLine2="        ~~~~~~~~~~~~~~~~~~~~~~~">
        <location
            file="src/main/res/menu/bottom_nav_menu.xml"
            line="15"
            column="9"/>
    </issue>

    <issue
        id="HardcodedText"
        message="Hardcoded string &quot;Add&quot;, should use `@string` resource"
        errorLine1="        android:title=&quot;Add&quot;"
        errorLine2="        ~~~~~~~~~~~~~~~~~~~">
        <location
            file="src/main/res/menu/bottom_nav_menu.xml"
            line="20"
            column="9"/>
    </issue>

    <issue
        id="HardcodedText"
        message="Hardcoded string &quot;Add a Book \nto Your Library&quot;, should use `@string` resource"
        errorLine1="        android:text=&quot;Add a Book \nto Your Library&quot;"
        errorLine2="        ~~~~~~~~~~~~~~~~~~~~~~~~~~~~~~~~~~~~~~~~~~~">
        <location
            file="src/main/res/layout/fragment_add_book.xml"
            line="25"
            column="9"/>
    </issue>

    <issue
        id="HardcodedText"
        message="Hardcoded string &quot;ISBN:&quot;, should use `@string` resource"
        errorLine1="            android:hint=&quot;ISBN:&quot;"
        errorLine2="            ~~~~~~~~~~~~~~~~~~~~">
        <location
            file="src/main/res/layout/fragment_add_book.xml"
            line="47"
            column="13"/>
    </issue>

    <issue
        id="HardcodedText"
        message="Hardcoded string &quot;Submit&quot;, should use `@string` resource"
        errorLine1="        android:text=&quot;Submit&quot;"
        errorLine2="        ~~~~~~~~~~~~~~~~~~~~~">
        <location
            file="src/main/res/layout/fragment_add_book.xml"
            line="85"
            column="9"/>
    </issue>

    <issue
        id="HardcodedText"
        message="Hardcoded string &quot; Libraries \n Near You&quot;, should use `@string` resource"
        errorLine1="            android:text=&quot; Libraries \n Near You&quot;"
        errorLine2="            ~~~~~~~~~~~~~~~~~~~~~~~~~~~~~~~~~~~~~">
        <location
            file="src/main/res/layout/fragment_home.xml"
            line="23"
            column="13"/>
    </issue>

    <issue
        id="HardcodedText"
        message="Hardcoded string &quot;Welcome&quot;, should use `@string` resource"
        errorLine1="                android:text=&quot;Welcome&quot;"
        errorLine2="                ~~~~~~~~~~~~~~~~~~~~~~">
        <location
            file="src/main/res/layout/fragment_landing_page.xml"
            line="26"
            column="17"/>
    </issue>

    <issue
        id="HardcodedText"
        message="Hardcoded string &quot;Log in&quot;, should use `@string` resource"
        errorLine1="                 android:text=&quot;Log in&quot;"
        errorLine2="                 ~~~~~~~~~~~~~~~~~~~~~">
        <location
            file="src/main/res/layout/fragment_landing_page.xml"
            line="42"
            column="18"/>
    </issue>

    <issue
        id="HardcodedText"
        message="Hardcoded string &quot;Not already a user?&quot;, should use `@string` resource"
        errorLine1="                android:text=&quot;Not already a user?&quot;"
        errorLine2="                ~~~~~~~~~~~~~~~~~~~~~~~~~~~~~~~~~~">
        <location
            file="src/main/res/layout/fragment_landing_page.xml"
            line="54"
            column="17"/>
    </issue>

    <issue
        id="HardcodedText"
        message="Hardcoded string &quot;Sign up&quot;, should use `@string` resource"
        errorLine1="                android:text=&quot;Sign up&quot;"
        errorLine2="                ~~~~~~~~~~~~~~~~~~~~~~">
        <location
            file="src/main/res/layout/fragment_landing_page.xml"
            line="71"
            column="17"/>
    </issue>

    <issue
        id="HardcodedText"
        message="Hardcoded string &quot;Login&quot;, should use `@string` resource"
        errorLine1="            android:text=&quot;Login&quot;"
        errorLine2="            ~~~~~~~~~~~~~~~~~~~~">
        <location
            file="src/main/res/layout/fragment_login.xml"
            line="33"
            column="13"/>
    </issue>

    <issue
        id="HardcodedText"
        message="Hardcoded string &quot;Email:&quot;, should use `@string` resource"
        errorLine1="                android:hint=&quot;Email:&quot;"
        errorLine2="                ~~~~~~~~~~~~~~~~~~~~~">
        <location
            file="src/main/res/layout/fragment_login.xml"
            line="56"
            column="17"/>
    </issue>

    <issue
        id="HardcodedText"
        message="Hardcoded string &quot;Password:&quot;, should use `@string` resource"
        errorLine1="                android:hint=&quot;Password:&quot;"
        errorLine2="                ~~~~~~~~~~~~~~~~~~~~~~~~">
        <location
            file="src/main/res/layout/fragment_login.xml"
            line="84"
            column="17"/>
    </issue>

    <issue
        id="HardcodedText"
        message="Hardcoded string &quot;Confirm&quot;, should use `@string` resource"
        errorLine1="            android:text=&quot;Confirm&quot;"
        errorLine2="            ~~~~~~~~~~~~~~~~~~~~~~">
        <location
            file="src/main/res/layout/fragment_login.xml"
            line="102"
            column="13"/>
    </issue>

</issues>
